LICENSE.txt
MANIFEST.in
README.rst
TODO.txt
example-bdp-defaults.cfg
setup.py
BicycleDataProcessor.egg-info/PKG-INFO
BicycleDataProcessor.egg-info/SOURCES.txt
BicycleDataProcessor.egg-info/dependency_links.txt
BicycleDataProcessor.egg-info/requires.txt
BicycleDataProcessor.egg-info/top_level.txt
bicycledataprocessor/__init__.py
bicycledataprocessor/bdpexceptions.py
bicycledataprocessor/database.py
bicycledataprocessor/main.py
bicycledataprocessor/signalprocessing.py
bicycledataprocessor/version.py
bicycledataprocessor/test/__init__.py
bicycledataprocessor/test/test_database.py
bicycledataprocessor/test/test_main.py
docs/bicycledataprocessor.rst
docs/bicycledataprocessor.test.rst
docs/index.rst
docs/installation.rst