Metadata-Version: 1.1
Name: BicycleDataProcessor
Version: 0.1.0
Summary: Processes the data collected from the instrumented bicycle.
Home-page: http://github.com/moorepants/BicycleDataProcessor
Author: Jason Keith Moore
Author-email: moorepants@gmail.com
License: LICENSE.txt
Platform: UNKNOWN
Classifier: Programming Language :: Python
Classifier: Programming Language :: Python :: 2.7
Classifier: Operating System :: OS Independent
Classifier: Development Status :: 4 - Beta
Classifier: Intended Audience :: Science/Research
Classifier: License :: OSI Approved :: BSD License
Classifier: Natural Language :: English
Classifier: Topic :: Scientific/Engineering
Classifier: Topic :: Scientific/Engineering :: Physics
